toptengen/__init__.py
toptengen/setup.py
toptengen-1.0.0.dist-info/METADATA
toptengen-1.0.0.dist-info/WHEEL
toptengen-1.0.0.dist-info/top_level.txt
toptengen-1.0.0.dist-info/RECORD
