Metadata-Version: 2.1
Name: toptengen
Version: 1.0.0
Summary: Simple!
Home-page: UNKNOWN
Author: GoodWorks Soft Co.
Author-email: <tylerfromgw@gmail.com>
License: UNKNOWN
Keywords: top ten maker,csvtools
Platform: UNKNOWN
Requires-Dist: pibrella
